Workbook

Sheet 1. Piloto 10 Muebles (Cierre)
B2: SIMULADOR COMERCIAL & PROPUESTA DE ARRANQUE (PILOTO 10 PRODUCTOS)
B3: Móveis Henn (Brasil) & Mario Mojica (3dBimFab) • Modelo de Co-Innovación
B5: 1. PARÁMETROS BASE DE INGENIERÍA & TARIFAS
B6: Salario Mensual Referencia (COP): | D6: 20000000 | E6: COP / mes
B7: Días Laborales Base / Mes: | D7: 30 | E7: días
B8: Valor Día de Ingeniería Senior: | D8: =D6/D7 | E8: COP / día ($ 666.667)
B9: TRM Dólar (COP / USD): | D9: 3300 | E9: COP por 1 USD
B10: Tasa de Cambio Real (BRL / USD): | D10: 5.14 | E10: BRL por 1 USD
B11: Tasa Directa COP / BRL: | D11: =D9/D10 | E11: COP por 1 BRL (~$ 642 COP)
B12: % Descuento Promocional en Manual 3D: | D12: 0.5 | E12: Descuento especial paquete piloto
B14: 2. MATRIZ DE DESARROLLO, CARGUE A 3dBimFab Y COSTOS POR CATEGORÍA
B15: Tipo de Mueble | C15: Rango Piezas | D15: Días 3BF | E15: Bloque Inteligente (Valor Real) | F15: Días Manual | G15: Manual 50% (Piloto) | H15: Costo Henn Actual | I15: Vr Henn (-30%) | J15: Ahorro vs Costo Actual | K15: % Ahorro Real
B16: Mueble Pequeño | C16: Máximo 10 | D16: 3 | E16: =D16* | F16: 0.5 | G16: =F16* | H16: 730733 | I16: 511513 | J16: =H16-G16 | K16: =(H16-G16)/H16
B17: Mueble Mediano | C17: Entre 11 a 24 | D17: 5 | E17: =D17* | F17: 0.8 | G17: =F17* | H17: 1124204 | I17: 786943 | J17: =H17-G17 | K17: =(H17-G17)/H17
B18: Mueble Grande | C18: Entre 25 y 40 | D18: 8 | E18: =D18* | F18: 1.1 | G18: =F18* | H18: 1517676 | I18: 1062373 | J18: =H18-G18 | K18: =(H18-G18)/H18
B21: 3. SIMULADOR DEL PAQUETE PILOTO DE 10 MUEBLES (DISTRIBUCIÓN REAL)
B22: Categoría Mueble | C22: Cant. Muebles | D22: Tarifa Manual Unit. (COP) | E22: Subtotal Manuales (COP) | F22: Valor 3BF Bonificado (100% OFF) | G22: Equivalente USD | H22: Equivalente BRL
B23: Muebles Pequeños (≤10 piezas) | C23: 2 | D23: =G16 | E23: =C23*D23 | F23: =C23*E16 | G23: =E23/ | H23: =E23/
B24: Muebles Medianos (11-24 piezas) | C24: 6 | D24: =G17 | E24: =C24*D24 | F24: =C24*E17 | G24: =E24/ | H24: =E24/
B25: Muebles Grandes (25-40 piezas) | C25: 2 | D25: =G18 | E25: =C25*D25 | F25: =C25*E18 | G25: =E25/ | H25: =E25/
B26: TOTAL PAQUETE PILOTO | C26: =SUM(C23:C25) | E26: =SUM(E23:E25) | F26: =SUM(F23:F25) | G26: =SUM(G23:G25) | H26: =SUM(H23:H25)
B29: 4. ESQUEMA DE CONDICIONES COMERCIALES Y HITOS DE PAGO
B30: Hito 1: Anticipo de Arranque (20%): | D30: =E26*0.20 | E30: A la firma de la orden de trabajo para inicio inmediato
B31: Hito 2: Saldo Final contra Entrega a Satisfacción (80%): | D31: =E26*0.80 | E31: A la entrega y validación de los 10 manuales en 30 días
B32: Valor Total Aportado / Bonificado por Mario en 3BF: | D32: =F26 | E32: 100% Bonificado ( COP para Henn en el piloto)

Sheet 1. Cotizador Henn (BRL)
B2: Simulador da Operação Anual de P&D | Móveis Henn
B4: Modelagem de Custos de Manuais de Montagem e Automação 3D | Proposta Mario Mojica (Reais BRL)
B5: MOEDA BASE DO CLIENTE: | D5: Reais (BRL - R$) | E5: Padrão de referência financeira para o mercado do Brasil
B6: CUSTO OPERAÇÃO HENN ATUAL | D6: PROPOSTA MARIO MOJICA (-30%) | F6: ECONOMIA LÍQUIDA PARA A HENN
B7: =D18 | D7: =B7*(1-D22) | F7: =B7-D7
B8: ="Média: " & TEXT(B7/D11, "R$ #,##0.00") & " / manual" | D8: ="Média: " & TEXT(D7/D11, "R$ #,##0.00") & " / manual" | F8: ="Economia: " & TEXT(F7/D11, "+R$ #,##0.00") & " / manual"
B10: 1. Parâmetros da Operação Atual da Henn (Células Azuis Editáveis)
B11: Total de Manuais / Lançamentos ao Ano: | D11: 80 | E11: manuais/ano | F11: Frequência estimada: ~16,7 manuais/mês
B12: Profissionais em P&D dedicados a manuais: | D12: 2 | E12: projetistas | F12: Equipe técnica em fábrica
B13: Salário Médio CLT + Encargos Sociais: | D13: 6000 | E13: R$/mês/pessoa | F13: Custo empresa mensal por projetista
B14: Licença SketchUp Pro / Studio (Anual/pessoa): | D14: 1200 | E14: R$/ano | F14: Licença anual de modelagem 3D
B15: Licença Adobe InDesign / CC (Anual/pessoa): | D15: 1800 | E15: R$/ano | F15: Licença anual de diagramação 2D
B16: Horas de Suporte P&D / SAC por mês (dúvidas montagem): | D16: 10 | E16: horas/mês | F16: Tempo de engenharia atendendo montadores
B18: TOTAL CUSTO ANUAL DA OPERAÇÃO HENN: | C18: (Folha + Licenças + Custo SAC) | D18: =(D12*D13*12) + (D12*(D14+D15)) + (D16*12*(D13/176)) | E18: =D18 | F18: ="Custo atual por manual: " & TEXT(D18/D11, "R$ #,##0.00")
B20: 2. Cenários de Economia Propostos por Mario Mojica
B22: Percentual de Redução Selecionado: | D22: 0.3 | E22: ← Pode alterar este percentual (ex: 10%, 20%, 30%, 40%, 50%)
B24: Cenário | C24: % Economia | D24: Proposta Mario (Ano) | E24: Custo / Manual | F24: Economia Líquida Henn (Ano) | G24: Economia / Manual
B25: Conservador | C25: 0.1 | D25: =$D$18*(1-C25) | E25: =D25/$D$11 | F25: =$D$18-D25 | G25: =F25/$D$11
B26: Moderado | C26: 0.2 | D26: =$D$18*(1-C26) | E26: =D26/$D$11 | F26: =$D$18-D26 | G26: =F26/$D$11
B27: Recomendado (Padrão Mario) | C27: 0.3 | D27: =$D$18*(1-C27) | E27: =D27/$D$11 | F27: =$D$18-D27 | G27: =F27/$D$11
B28: Otimizado | C28: 0.4 | D28: =$D$18*(1-C28) | E28: =D28/$D$11 | F28: =$D$18-D28 | G28: =F28/$D$11
B29: Agressivo (Escala Máxima) | C29: 0.5 | D29: =$D$18*(1-C29) | E29: =D29/$D$11 | F29: =$D$18-D29 | G29: =F29/$D$11
B31: 3. Detalhamento por Faixa de Peças e Complexidade de Produto RTA
B33: Faixa de Peças / Categoria | C33: Fator Ponderado | D33: Custo Interno Henn | E33: Proposta Mario (-30%) | F33: Economia Unitária | G33: Exemplo de Produtos Henn
B34: Pequeno: Até 10 peças (~1 dia / Simples) | C34: 0.65 | D34: =C34 * ($D$18 / $D$11) | E34: =C34 * ($D$7 / $D$11) | F34: =D34 - E34 | G34: Criado-Mudo, Nichos, Painel Simples
B35: Médio: 11 a 24 peças (~1,5 dias / Média Henn ~20 peças) | C35: 1 | D35: =C35 * ($D$18 / $D$11) | E35: =C35 * ($D$7 / $D$11) | F35: =D35 - E35 | G35: Rack TV, Buffet, Cômoda 4 Gavetas
B36: Grande / Complexo: 25 a 40 peças (~2 dias / Multimódulo) | C36: 1.35 | D36: =C36 * ($D$18 / $D$11) | E36: =C36 * ($D$7 / $D$11) | F36: =D36 - E36 | G36: Guarda-Roupa 6 Portas, Cozinha Modulada

Sheet 2. Cotizador Henn (USD)
B2: Cotizador Internacional de P&D | Móveis Henn (En Dólares USD)
B4: Moneda de Negociación y Facturación Internacional B2B (Convertido desde Reais vía TRM BRL ➔ USD)
B5: TASA DE CAMBIO TRM (BRL por 1 USD): | D5: 5.14 | E5: ← Edita aquí la TRM BRL / USD según la tasa del mercado
B6: COSTO OPERACIÓN HENN ACTUAL (USD) | D6: PROPUESTA MARIO MOJICA (-30% USD) | F6: AHORRO NETO PARA HENN (USD)
B7: =D18 | D7: =B7*(1-D22) | F7: =B7-D7
B8: ="Promedio: " & TEXT(B7/D11, "$ #,##0.00") & " / manual" | D8: ="Promedio: " & TEXT(D7/D11, "$ #,##0.00") & " / manual" | F8: ="Ahorro: " & TEXT(F7/D11, "+$ #,##0.00") & " / manual"
B10: 1. Parámetros de la Operación Convertidos a Dólares (USD)
B11: Total Manuales / Lanzamientos al Año: | D11: ='1. Cotizador Henn (BRL)'!D11 | E11: manuales/año | F11: Sincronizado de celda D11 pestaña BRL
B12: Personas en P&D dedicadas a manuales: | D12: ='1. Cotizador Henn (BRL)'!D12 | E12: diseñadores | F12: Sincronizado de celda D12 pestaña BRL
B13: Salario Promedio CLT + Cargas Sociales (USD): | D13: ='1. Cotizador Henn (BRL)'!D13 / $D$5 | E13: USD/mes/persona | F13: Convertido vía TRM BRL ➔ USD
B14: Licencia SketchUp Pro / Studio (Anual USD): | D14: ='1. Cotizador Henn (BRL)'!D14 / $D$5 | E14: USD/año | F14: Convertido vía TRM BRL ➔ USD
B15: Licencia Adobe InDesign / CC (Anual USD): | D15: ='1. Cotizador Henn (BRL)'!D15 / $D$5 | E15: USD/año | F15: Convertido vía TRM BRL ➔ USD
B16: Horas de Soporte P&D / SAC al mes por dudas: | D16: ='1. Cotizador Henn (BRL)'!D16 | E16: horas/mes | F16: Sincronizado de celda D16 pestaña BRL
B18: TOTAL COSTO ANUAL OPERACIÓN HENN (USD): | C18: (Masa Salarial + Licencias + Costo SAC) | D18: ='1. Cotizador Henn (BRL)'!D18 / $D$5 | E18: =D18 | F18: ="Costo actual por manual: " & TEXT(D18/D11, "$ #,##0.00")
B20: 2. Escenarios de Ahorro y Propuesta en Dólares (USD)
B22: Porcentaje de Reducción Seleccionado: | D22: ='1. Cotizador Henn (BRL)'!D22 | E22: Sincronizado con porcentaje de reducción seleccionado (D22)
B24: Escenario Comercial | C24: % Ahorro | D24: Propuesta Mario (Año USD) | E24: Costo / Manual (USD) | F24: Ahorro Neto Henn (Año USD) | G24: Ahorro / Manual (USD)
B25: Conservador (10%) | C25: ='1. Cotizador Henn (BRL)'!C25 | D25: ='1. Cotizador Henn (BRL)'!D25 / $D$5 | E25: =D25/$D$11 | F25: ='1. Cotizador Henn (BRL)'!F25 / $D$5 | G25: =F25/$D$11
B26: Moderado (20%) | C26: ='1. Cotizador Henn (BRL)'!C26 | D26: ='1. Cotizador Henn (BRL)'!D26 / $D$5 | E26: =D26/$D$11 | F26: ='1. Cotizador Henn (BRL)'!F26 / $D$5 | G26: =F26/$D$11
B27: ⭐ Recomendado (30% - Estándar Mario) | C27: ='1. Cotizador Henn (BRL)'!C27 | D27: ='1. Cotizador Henn (BRL)'!D27 / $D$5 | E27: =D27/$D$11 | F27: ='1. Cotizador Henn (BRL)'!F27 / $D$5 | G27: =F27/$D$11
B28: Optimizado (40%) | C28: ='1. Cotizador Henn (BRL)'!C28 | D28: ='1. Cotizador Henn (BRL)'!D28 / $D$5 | E28: =D28/$D$11 | F28: ='1. Cotizador Henn (BRL)'!F28 / $D$5 | G28: =F28/$D$11
B29: Agresivo (50%) | C29: ='1. Cotizador Henn (BRL)'!C29 | D29: ='1. Cotizador Henn (BRL)'!D29 / $D$5 | E29: =D29/$D$11 | F29: ='1. Cotizador Henn (BRL)'!F29 / $D$5 | G29: =F29/$D$11
B31: 3. Desglose por Rango de Piezas y Complejidad de Mueble RTA (En Dólares USD)
B33: Rango de Piezas / Categoría | C33: Factor Ponderado | D33: Costo Interno Henn (USD) | E33: Propuesta Mario (USD) | F33: Ahorro Unitario (USD) | G33: Ejemplo de Productos Henn
B34: Pequeño: Hasta 10 piezas (~1 día / Simple) | C34: ='1. Cotizador Henn (BRL)'!C34 | D34: ='1. Cotizador Henn (BRL)'!D34 / $D$5 | E34: ='1. Cotizador Henn (BRL)'!E34 / $D$5 | F34: ='1. Cotizador Henn (BRL)'!F34 / $D$5 | G34: ='1. Cotizador Henn (BRL)'!G34
B35: Mediano: 11 a 24 piezas (~1,5 días / Promedio Henn ~20 piezas) | C35: ='1. Cotizador Henn (BRL)'!C35 | D35: ='1. Cotizador Henn (BRL)'!D35 / $D$5 | E35: ='1. Cotizador Henn (BRL)'!E35 / $D$5 | F35: ='1. Cotizador Henn (BRL)'!F35 / $D$5 | G35: ='1. Cotizador Henn (BRL)'!G35
B36: Grande / Complejo: 25 a 40 piezas (~2 días / Multimódulo) | C36: ='1. Cotizador Henn (BRL)'!C36 | D36: ='1. Cotizador Henn (BRL)'!D36 / $D$5 | E36: ='1. Cotizador Henn (BRL)'!E36 / $D$5 | F36: ='1. Cotizador Henn (BRL)'!F36 / $D$5 | G36: ='1. Cotizador Henn (BRL)'!G36

Sheet 3. Cotizador Henn (COP)
B2: Cotizador Nacional de P&D | Móveis Henn (En Pesos Colombianos COP)
B4: Conversión de Dólares (USD) a Pesos Colombianos (COP) vía Tasa Representativa del Mercado (TRM)
B5: TASA DE CAMBIO TRM (COP por 1 USD): | D5: 3000 | E5: ← Edita aquí la TRM COP / USD según la tasa del mercado
B6: COSTO OPERACIÓN HENN ACTUAL (COP) | D6: PROPUESTA MARIO MOJICA (-30% COP) | F6: AHORRO NETO PARA HENN (COP)
B7: =D18 | D7: =B7*(1-D22) | F7: =B7-D7
B8: ="Promedio: " & TEXT(B7/D11, "$ #,##0") & " / manual" | D8: ="Promedio: " & TEXT(D7/D11, "$ #,##0") & " / manual" | F8: ="Ahorro: " & TEXT(F7/D11, "+$ #,##0") & " / manual"
B10: 1. Parámetros de la Operación Convertidos a Pesos Colombianos (COP)
B11: Total Manuales / Lanzamientos al Año: | D11: ='1. Cotizador Henn (BRL)'!D11 | E11: manuales/año | F11: Sincronizado de celda D11 pestaña BRL
B12: Personas en P&D dedicadas a manuales: | D12: ='1. Cotizador Henn (BRL)'!D12 | E12: diseñadores | F12: Sincronizado de celda D12 pestaña BRL
B13: Salario Promedio CLT + Cargas Sociales (COP): | D13: ='2. Cotizador Henn (USD)'!D13 * $D$5 | E13: COP/mes/persona | F13: Convertido vía TRM USD ➔ COP
B14: Licencia SketchUp Pro / Studio (Anual COP): | D14: ='2. Cotizador Henn (USD)'!D14 * $D$5 | E14: COP/año | F14: Convertido vía TRM USD ➔ COP
B15: Licencia Adobe InDesign / CC (Anual COP): | D15: ='2. Cotizador Henn (USD)'!D15 * $D$5 | E15: COP/año | F15: Convertido vía TRM USD ➔ COP
B16: Horas de Soporte P&D / SAC al mes por dudas: | D16: ='1. Cotizador Henn (BRL)'!D16 | E16: horas/mes | F16: Sincronizado de celda D16 pestaña BRL
B18: TOTAL COSTO ANUAL OPERACIÓN HENN (COP): | C18: (Masa Salarial + Licencias + Costo SAC) | D18: ='2. Cotizador Henn (USD)'!D18 * $D$5 | E18: =D18 | F18: ="Costo actual por manual: " & TEXT(D18/D11, "$ #,##0")
B20: 2. Escenarios de Ahorro y Propuesta en Pesos Colombianos (COP)
B22: Porcentaje de Reducción Seleccionado: | D22: 0.5 | E22: Sincronizado con porcentaje de reducción seleccionado (D22)
B24: Escenario Comercial | C24: % Ahorro | D24: Propuesta Mario (Año COP) | E24: Costo / Manual (COP) | F24: Ahorro Neto Henn (Año COP) | G24: Ahorro / Manual (COP)
B25: Conservador (10%) | C25: ='1. Cotizador Henn (BRL)'!C25 | D25: ='2. Cotizador Henn (USD)'!D25 * $D$5 | E25: =D25/$D$11 | F25: ='2. Cotizador Henn (USD)'!F25 * $D$5 | G25: =F25/$D$11
B26: Moderado (20%) | C26: ='1. Cotizador Henn (BRL)'!C26 | D26: ='2. Cotizador Henn (USD)'!D26 * $D$5 | E26: =D26/$D$11 | F26: ='2. Cotizador Henn (USD)'!F26 * $D$5 | G26: =F26/$D$11
B27: ⭐ Recomendado (30% - Estándar Mario) | C27: ='1. Cotizador Henn (BRL)'!C27 | D27: ='2. Cotizador Henn (USD)'!D27 * $D$5 | E27: =D27/$D$11 | F27: ='2. Cotizador Henn (USD)'!F27 * $D$5 | G27: =F27/$D$11
B28: Optimizado (40%) | C28: ='1. Cotizador Henn (BRL)'!C28 | D28: ='2. Cotizador Henn (USD)'!D28 * $D$5 | E28: =D28/$D$11 | F28: ='2. Cotizador Henn (USD)'!F28 * $D$5 | G28: =F28/$D$11
B29: Agresivo (50%) | C29: ='1. Cotizador Henn (BRL)'!C29 | D29: ='2. Cotizador Henn (USD)'!D29 * $D$5 | E29: =D29/$D$11 | F29: ='2. Cotizador Henn (USD)'!F29 * $D$5 | G29: =F29/$D$11
B31: 3. Desglose por Rango de Piezas y Complejidad de Mueble RTA (En Pesos Colombianos)
B33: Rango de Piezas / Categoría | C33: Factor Ponderado | D33: Costo Interno Henn (COP) | E33: Propuesta Mario (COP) | F33: Ahorro Unitario (COP) | G33: Ejemplo de Productos Henn
B34: Pequeño: Hasta 10 piezas (~1 día / Simple) | C34: ='1. Cotizador Henn (BRL)'!C34 | D34: =C34 * ($D$18 / $D$11) | E34: =C34 * ($D$7 / $D$11) | F34: =D34 - E34 | G34: ='1. Cotizador Henn (BRL)'!G34
B35: Mediano: 11 a 24 piezas (~1,5 días / Promedio Henn ~20 piezas) | C35: ='1. Cotizador Henn (BRL)'!C35 | D35: =C35 * ($D$18 / $D$11) | E35: =C35 * ($D$7 / $D$11) | F35: =D35 - E35 | G35: ='1. Cotizador Henn (BRL)'!G35
B36: Grande / Complejo: 25 a 40 piezas (~2 días / Multimódulo) | C36: ='1. Cotizador Henn (BRL)'!C36 | D36: =C36 * ($D$18 / $D$11) | E36: =C36 * ($D$7 / $D$11) | F36: =D36 - E36 | G36: ='1. Cotizador Henn (BRL)'!G36

Sheet 4. Rentabilidad Mario (COP)
B2: Análisis de Rentabilidad e Ingresos Reales en Pesos Colombianos (COP)
B4: Conversión Cambiaria B2B (USD ➔ COP), Facturación Proyectada y Ganancia Neta para Mario Mojica
B6: FACTURACIÓN ANUAL ESTIMADA (COP) | D6: FACTURACIÓN MENSUAL PROMEDIO (COP) | F6: INGRESO PROMEDIO POR MANUAL (COP)
B7: ='3. Cotizador Henn (COP)'!D7 | D7: =B7 / 12 | F7: =B7 / '1. Cotizador Henn (BRL)'!D11
B8: ="Equivalente a: " & TEXT('2. Cotizador Henn (USD)'!D7, "$ #,##0.00") & " USD" | D8: ="Por mes (~16.7 manuales/mes)" | F8: ="Equivalente a: " & TEXT('2. Cotizador Henn (USD)'!D7/'1. Cotizador Henn (BRL)'!D11, "$ #,##0.00") & " USD"
B10: 1. Parámetros Cambiarios y Costos Operativos de Mario (Celdas Celestes Editables)
B11: Tasa de Cambio TRM USD / COP (Sincronizada): | D11: ='3. Cotizador Henn (COP)'!$D$5 | E11: COP / USD | F11: Tasa tomada de la celda de control TRM COP
B12: Costo Servidores / VPS / Hosting / Dominio (Mensual): | D12: 350000 | E12: COP / mes | F12: Infraestructura VPS, Supabase y motor 3dBimFab
B13: Gastos Bancarios / Swift / Impuestos Transaccionales (%): | D13: 0.04 | E13: % facturación | F13: Comisión bancaria de transferencia y 4x1000
B15: GANANCIA NETA REAL PROYECTADA (AÑO): | C15: (Facturación - Servidores - Comisiones) | D15: =B7*(1-D13) - (D12*12) | E15: =D15 / 12 | F15: ="Margen Neto: " & TEXT(D15/B7, "0.0%") & " de rentabilidad"
B17: 2. Proyección de Ingresos en Pesos (COP) según Escenario Comercial Acordado con Henn
B19: Escenario Comercial | C19: % Descuento Henn | D19: Facturación Anual (USD) | E19: Facturación Anual (COP) | F19: Ingreso Mensual (COP) | G19: Ingreso / Manual (COP)
B25: Conservador (10% descuento) | C25: ='3. Cotizador Henn (COP)'!C25 | D25: ='2. Cotizador Henn (USD)'!D25 | E25: ='3. Cotizador Henn (COP)'!D25 | F25: =E25 / 12 | G25: ='3. Cotizador Henn (COP)'!E25
B26: 3. Simulación de Escala B2B Multicliente en Brasil (Potencial Total en COP)
B27: ⭐ Recomendado (30% descuento - Estándar Mario) | C27: ='3. Cotizador Henn (COP)'!C27 | D27: ='2. Cotizador Henn (USD)'!D27 | E27: ='3. Cotizador Henn (COP)'!D27 | F27: =E27 / 12 | G27: ='3. Cotizador Henn (COP)'!E27
B28: Volumen de Fabricantes | C28: Empresas en Brasil | D28: Facturación Anual (USD) | E28: Facturación Anual (COP) | F28: Ingreso Mensual (COP) | G28: Ganancia Neta Anual (COP)
B29: 1 Fabricante (Piloto) | C29: Móveis Henn | D29: ='2. Cotizador Henn (USD)'!D27 * 1 | E29: =D29 * '3. Cotizador Henn (COP)'!$D$5 | F29: =E29 / 12 | G29: =E29*(1-$D$13) - ($D$12*12*1*0.4)
B30: 2 Fabricantes | C30: Henn + Politorno | D30: ='2. Cotizador Henn (USD)'!D27 * 2 | E30: =D30 * '3. Cotizador Henn (COP)'!$D$5 | F30: =E30 / 12 | G30: =E30*(1-$D$13) - ($D$12*12*2*0.4)
B31: 3 Fabricantes | C31: Henn + Politorno + Kappesberg | D31: ='2. Cotizador Henn (USD)'!D27 * 3 | E31: =D31 * '3. Cotizador Henn (COP)'!$D$5 | F31: =E31 / 12 | G31: =E31*(1-$D$13) - ($D$12*12*3*0.4)
B32: 5 Fabricantes | C32: Top 5 Empresas RTA Brasil | D32: ='2. Cotizador Henn (USD)'!D27 * 5 | E32: =D32 * '3. Cotizador Henn (COP)'!$D$5 | F32: =E32 / 12 | G32: =E32*(1-$D$13) - ($D$12*12*5*0.4)
B33: 10 Fabricantes | C33: Consolidación Sectorial RTA | D33: ='2. Cotizador Henn (USD)'!D27 * 10 | E33: =D33 * '3. Cotizador Henn (COP)'!$D$5 | F33: =E33 / 12 | G33: =E33*(1-$D$13) - ($D$12*12*10*0.4)
